{"title":"华为nova5i来了：极点全面屏+麒麟710 - 华为,nova5i,麒麟710 - IT之家","link":"https://www.ithome.com/0/429/524.htm","meta":{"status":200,"responseHeaders":{"server":"JSP3/2.0.14","date":"Fri, 21 Jun 2019 11:26:25 GMT","content-type":"text/html; charset=utf-8","transfer-encoding":"chunked","connection":"close","content-encoding":"gzip","accept-ranges":"bytes","cache-control":"private","x-aspnet-version":"4.0.30319","ohc-response-time":"1 0 17 58 76 76","ohc-file-size":"20381","alt-svc":"quic=\":443\"; ma=2592000; v=\"43,42,39\"","ohc-cache-hit":"dyct51 [1], xactcache51 [4]"},"finalUrl":"https://www.ithome.com/0/429/524.htm","redirectCount":0,"cookieJar":{"options":{"sessionTimeout":1800},"cookies":{}}},"imgs":["https://img.ithome.com/newsuploadfiles/2019/6/20190621_155353_937.jpg","https://img.ithome.com/newsuploadfiles/2019/6/20190621_155251_177.jpg","https://img.ithome.com/newsuploadfiles/2019/6/20190621_155259_566.jpg"],"text":"IT之家6月21日消息 在今天进行的华为nova5系列发布会上，除了华为nova5/nova5 Pro外，华为还推出了全新的nova5i。华为nova5i采用了一块6.4英寸极点全面屏，搭载麒麟710处理器。屏占比达到90.6%，手机背面有S形炫光纹理。华为nova5i前置2400万微塑美拍，AI立体美颜。华为nova5i配备多场景AI四摄，多场景拍摄智能切换。四颗摄像头分别为2400万高清镜头、800万超广角镜头、200万微距镜头以及200万景深镜头。"}